django_nl_filter-1.0.dist-info/licenses/LICENSE
nlf/__init__.py
nlf/filter.py
nlf/parser.py
nlf/registry.py
nlf/utils.py
django_nl_filter-1.0.dist-info/METADATA
django_nl_filter-1.0.dist-info/WHEEL
django_nl_filter-1.0.dist-info/top_level.txt
django_nl_filter-1.0.dist-info/RECORD
