Metadata-Version: 2.4
Name: django-nl-filter
Version: 1.0
Summary: Natural Language Filtering for Django ORM
Home-page: https://github.com/arjun-vs/django-nl-filter
Author: Arjun V S
Author-email: Arjun V S <arjunvs.vs@gmail.com>
License: MIT License
Requires-Python: >=3.7
License-File: LICENSE
Requires-Dist: Django>=3.2
Dynamic: author
Dynamic: home-page
Dynamic: license-file
Dynamic: requires-python
